xh_py_project_versioning/PyPiRepo.py
xh_py_project_versioning/PyProject.py
xh_py_project_versioning/__init__.py
xh_py_project_versioning/__main__.py
xh_py_project_versioning/versioning.py
xh_py_project_versioning-0.0.6.dist-info/LICENSE.txt
xh_py_project_versioning-0.0.6.dist-info/METADATA
xh_py_project_versioning-0.0.6.dist-info/WHEEL
xh_py_project_versioning-0.0.6.dist-info/top_level.txt
xh_py_project_versioning-0.0.6.dist-info/RECORD
