Metadata-Version: 2.1
Name: xh-py-project-versioning
Version: 0.0.6
Summary: A library for increate version number and check version mismatch
Author-email: xethhung <pypi@xethh.dev>
Project-URL: Homepage, https://github.com/xh-dev/xh-py-project-versioning
Project-URL: Bug Tracker, https://github.com/xh-dev/xh-py-project-versioning
Classifier: Programming Language :: Python :: 3
Classifier: License :: OSI Approved :: MIT License
Classifier: Operating System :: OS Independent
Requires-Python: >=3.6
License-File: LICENSE.txt
Requires-Dist: toml >=0.10.2
Requires-Dist: GitPython >=3.1.31
